abseil_dll.dll
re2.cp311-win_amd64.pyd
re2.dll
re2.pdb
pyre2-0.3.10.dist-info/licenses/LICENSE
pyre2-0.3.10.dist-info/METADATA
pyre2-0.3.10.dist-info/WHEEL
pyre2-0.3.10.dist-info/top_level.txt
pyre2-0.3.10.dist-info/RECORD
