Metadata-Version: 2.4
Name: pyre2
Version: 0.3.10
Summary: Python wrapper for Google RE2 library using Cython
Home-page: https://github.com/andreasvc/pyre2
Author: Andreas van Cranenburgh
Author-email: andreas@unstable.nl
Maintainer: Steve Arnold
Maintainer-email: nerdboy@gentoo.org
License: BSD
Classifier: License :: OSI Approved :: BSD License
Classifier: Programming Language :: Cython
Classifier: Programming Language :: Python :: 3.10
Classifier: Intended Audience :: Developers
Classifier: Topic :: Software Development :: Libraries :: Python Modules
Requires-Python: >=3.10
License-File: LICENSE
Provides-Extra: doc
Requires-Dist: sphinx; extra == "doc"
Requires-Dist: sphinx_rtd_theme; extra == "doc"
Requires-Dist: sphinxcontrib-apidoc; extra == "doc"
Provides-Extra: test
Requires-Dist: pytest; extra == "test"
Provides-Extra: perf
Requires-Dist: regex; extra == "perf"
Dynamic: license-file
